cloudpail/__init__.py
cloudpail/main.py
cloudpail-1.0.9.dist-info/licenses/LICENSE
cloudpail-1.0.9.dist-info/METADATA
cloudpail-1.0.9.dist-info/WHEEL
cloudpail-1.0.9.dist-info/entry_points.txt
cloudpail-1.0.9.dist-info/top_level.txt
cloudpail-1.0.9.dist-info/RECORD
