Metadata-Version: 2.4
Name: cloudpail
Version: 1.0.9
Summary: The Developer-First CLI for AWS S3 Management.
Author-email: shakeelsaga <shakeelmohammedofficial@gmail.com>
Project-URL: Homepage, https://github.com/shakeelsaga/CloudPail
Project-URL: Issues, https://github.com/shakeelsaga/CloudPail/issues
Project-URL: icon, https://cdn.jsdelivr.net/gh/shakeelsaga/CloudPail@main/assets/CloudPail-Logo-Without-Background.png
Classifier: Programming Language :: Python :: 3
Classifier: License :: OSI Approved :: MIT License
Classifier: Operating System :: OS Independent
Classifier: Topic :: Utilities
Classifier: Environment :: Console
Classifier: Intended Audience :: Developers
Classifier: Intended Audience :: System Administrators
Requires-Python: >=3.8
License-File: LICENSE
Requires-Dist: boto3
Requires-Dist: rich
Requires-Dist: InquirerPy
Requires-Dist: pyperclip
Dynamic: license-file
